guido/__init__.py
guido/__main__.py
guido/commands.py
guido/guido.py
guido/importer.py
guido/logconfig.py
guido/messages.py
guido_kafka-0.2.1.dist-info/LICENSE
guido_kafka-0.2.1.dist-info/METADATA
guido_kafka-0.2.1.dist-info/WHEEL
guido_kafka-0.2.1.dist-info/entry_points.txt
guido_kafka-0.2.1.dist-info/top_level.txt
guido_kafka-0.2.1.dist-info/RECORD
