Metadata-Version: 2.1
Name: guido-kafka
Version: 0.2.1
License-File: LICENSE
Requires-Dist: kafka-python ==2.0.2
